{"total_time_ns":202418333,"total_allocated_bytes":13101992,"time_ns":0,"n_calls":0,"allocated_bytes":0,"inner_timers":{"Cell averaging":{"total_time_ns":0,"total_allocated_bytes":0,"time_ns":3026353,"n_calls":48,"allocated_bytes":0,"inner_timers":{}},"Time step computation":{"total_time_ns":0,"total_allocated_bytes":0,"time_ns":3710,"n_calls":47,"allocated_bytes":0,"inner_timers":{}},"Write solution":{"total_time_ns":0,"total_allocated_bytes":0,"time_ns":74911596,"n_calls":2,"allocated_bytes":13095448,"inner_timers":{}},"Update ghost values":{"total_time_ns":0,"total_allocated_bytes":0,"time_ns":307954,"n_calls":47,"allocated_bytes":0,"inner_timers":{}},"Compute error":{"total_time_ns":0,"total_allocated_bytes":0,"time_ns":7544437,"n_calls":2,"allocated_bytes":5792,"inner_timers":{}},"Limiter":{"total_time_ns":4399,"total_allocated_bytes":0,"time_ns":19557,"n_calls":95,"allocated_bytes":752,"inner_timers":{"Pre process limiter":{"total_time_ns":0,"total_allocated_bytes":0,"time_ns":4399,"n_calls":47,"allocated_bytes":0,"inner_timers":{}}}},"Face residual":{"total_time_ns":0,"total_allocated_bytes":0,"time_ns":19419861,"n_calls":47,"allocated_bytes":0,"inner_timers":{}},"Cell Residual":{"total_time_ns":0,"total_allocated_bytes":0,"time_ns":96540537,"n_calls":47,"allocated_bytes":0,"inner_timers":{}},"Update solution":{"total_time_ns":0,"total_allocated_bytes":0,"time_ns":254316,"n_calls":47,"allocated_bytes":0,"inner_timers":{}},"Time Step computation":{"total_time_ns":0,"total_allocated_bytes":0,"time_ns":390012,"n_calls":47,"allocated_bytes":0,"inner_timers":{}}}}