{"total_time_ns":20253306712,"total_allocated_bytes":58220216,"time_ns":0,"n_calls":0,"allocated_bytes":0,"inner_timers":{"Cell averaging":{"total_time_ns":0,"total_allocated_bytes":0,"time_ns":452330927,"n_calls":298,"allocated_bytes":0,"inner_timers":{}},"Time step computation":{"total_time_ns":0,"total_allocated_bytes":0,"time_ns":27089,"n_calls":297,"allocated_bytes":0,"inner_timers":{}},"Write solution":{"total_time_ns":0,"total_allocated_bytes":0,"time_ns":300066978,"n_calls":2,"allocated_bytes":58213672,"inner_timers":{}},"Update ghost values":{"total_time_ns":0,"total_allocated_bytes":0,"time_ns":11845551,"n_calls":297,"allocated_bytes":0,"inner_timers":{}},"Compute error":{"total_time_ns":0,"total_allocated_bytes":0,"time_ns":109815491,"n_calls":2,"allocated_bytes":5792,"inner_timers":{}},"Limiter":{"total_time_ns":44433,"total_allocated_bytes":0,"time_ns":167051,"n_calls":595,"allocated_bytes":752,"inner_timers":{"Pre process limiter":{"total_time_ns":0,"total_allocated_bytes":0,"time_ns":44433,"n_calls":297,"allocated_bytes":0,"inner_timers":{}}}},"Face residual":{"total_time_ns":0,"total_allocated_bytes":0,"time_ns":2589962693,"n_calls":297,"allocated_bytes":0,"inner_timers":{}},"Cell Residual":{"total_time_ns":0,"total_allocated_bytes":0,"time_ns":16650899484,"n_calls":297,"allocated_bytes":0,"inner_timers":{}},"Update solution":{"total_time_ns":0,"total_allocated_bytes":0,"time_ns":105969535,"n_calls":297,"allocated_bytes":0,"inner_timers":{}},"Time Step computation":{"total_time_ns":0,"total_allocated_bytes":0,"time_ns":32221913,"n_calls":297,"allocated_bytes":0,"inner_timers":{}}}}